LICENSE.md
README.md
setup.py
poncipher/__init__.py
poncipher/poncipher.py
poncipher.egg-info/PKG-INFO
poncipher.egg-info/SOURCES.txt
poncipher.egg-info/dependency_links.txt
poncipher.egg-info/top_level.txt