Metadata-Version: 2.1
Name: poncipher
Version: 1.0
Summary: PonCipher is library for encoding data (include your Python projects)
Author: Its-MatriX
Keywords: cipher encoder encoder-decoder
Classifier: License :: OSI Approved :: MIT License
Requires-Python: >=3
License-File: LICENSE.md
